[
  {
    "Type": "Texture2D",
    "Name": "statusIcon_sacrificedBlood",
    "Properties": {
      "ImportedSize": {
        "X": 150,
        "Y": 150
      },
      "LightingGuid": "3F8D6347-469C8C7C-8F8DE7A6-50EDCB43",
      "CompressionSettings": "TC_EditorIcon",
      "LODGroup": "TEXTUREGROUP_UI",
      "NeverStream": true
    },
    "SizeX": 150,
    "SizeY": 150,
    "PackedData": 1,
    "PixelFormat": "PF_B8G8R8A8",
    "FirstMipToSerialize": 0,
    "Mips": [
      {
        "BulkData": {
          "BulkDataFlags": "BULKDATA_ForceInlinePayload",
          "ElementCount": 90000,
          "SizeOnDisk": 90000,
          "OffsetInFile": "0x169C0"
        },
        "SizeX": 150,
        "SizeY": 150,
        "SizeZ": 1
      }
    ]
  }
]