[
  {
    "Type": "BodySetup",
    "Name": "BodySetup_278",
    "Outer": "sm_brick_04",
    "Properties": {
      "AggGeom": {
        "ConvexElems": [
          {
            "VertexData": [
              {
                "X": 5.7612343,
                "Y": 5.125,
                "Z": 0.0112345815
              },
              {
                "X": 5.754156,
                "Y": -5.1347065,
                "Z": 0.030648708
              },
              {
                "X": 5.75,
                "Y": -5.144413,
                "Z": 5.25
              },
              {
                "X": 5.75,
                "Y": 5.144414,
                "Z": 5.1875
              },
              {
                "X": -5.7541475,
                "Y": -0.13853598,
                "Z": 4.6419687
              },
              {
                "X": -5.7541475,
                "Y": -0.13853645,
                "Z": 5.2195644
              },
              {
                "X": -5.752074,
                "Y": -5.144413,
                "Z": 5.1875
              },
              {
                "X": -5.7541475,
                "Y": -5.1347065,
                "Z": 4.6419687
              },
              {
                "X": -0.4711976,
                "Y": 5.144414,
                "Z": 0.030648928
              },
              {
                "X": -0.47119713,
                "Y": 5.144414,
                "Z": 5.221305
              },
              {
                "X": -1.142827,
                "Y": -5.144413,
                "Z": 0.030648017
              },
              {
                "X": -0.6121793,
                "Y": -4.6137657,
                "Z": -0.5
              },
              {
                "X": 5.25,
                "Y": -4.6137652,
                "Z": -0.49999997
              },
              {
                "X": 5.2499995,
                "Y": 4.6137652,
                "Z": -0.5
              },
              {
                "X": -0.6121788,
                "Y": 4.6137652,
                "Z": -0.5
              },
              {
                "X": -0.8013951,
                "Y": 4.814216,
                "Z": -0.31078398
              },
              {
                "X": 5.688163,
                "Y": -5.0631614,
                "Z": -0.061837524
              }
            ],
            "IndexData": [],
            "ElemBox": {
              "Min": {
                "X": -5.7541475,
                "Y": -5.144413,
                "Z": -0.5
              },
              "Max": {
                "X": 5.7612343,
                "Y": 5.144414,
                "Z": 5.25
              },
              "IsValid": 1
            },
            "Transform": {
              "Rotation": {
                "X": 0.0,
                "Y": 0.0,
                "Z": 0.0,
                "W": 1.0,
                "IsNormalized": true,
                "Size": 1.0,
                "SizeSquared": 1.0
              },
              "Translation": {
                "X": 0.0,
                "Y": 0.0,
                "Z": 0.0
              },
              "Scale3D": {
                "X": 1.0,
                "Y": 1.0,
                "Z": 1.0
              }
            },
            "RestOffset": 0.0,
            "Name": "None",
            "bContributeToMass": true
          }
        ]
      },
      "DefaultInstance": {
        "ObjectType": "ECC_WorldStatic",
        "CollisionProfileName": "BlockAll",
        "CollisionResponses": {
          "ResponseArray": [
            {
              "Channel": "Interactable",
              "Response": "ECR_Block"
            },
            {
              "Channel": "Slasher",
              "Response": "ECR_Block"
            },
            {
              "Channel": "Blood",
              "Response": "ECR_Block"
            },
            {
              "Channel": "InteractionDetector",
              "Response": "ECR_Ignore"
            },
            {
              "Channel": "BlinkBlocker",
              "Response": "ECR_Ignore"
            },
            {
              "Channel": "Ground",
              "Response": "ECR_Ignore"
            },
            {
              "Channel": "Walkable",
              "Response": "ECR_Block"
            }
          ]
        }
      }
    },
    "BodySetupGuid": "37A4B5074F252DB80D95CC898B55E500",
    "CookedFormatData": {
      "PhysXGeneric": {
        "BulkDataFlags": "BULKDATA_ForceInlinePayload",
        "ElementCount": 6897,
        "SizeOnDisk": 6897,
        "OffsetInFile": "0x6203"
      }
    }
  },
  {
    "Type": "NavCollision",
    "Name": "NavCollision_9",
    "Outer": "sm_brick_04",
    "CookedFormatData": {
      "NavCollision_X": {
        "BulkDataFlags": "BULKDATA_ForceInlinePayload",
        "ElementCount": 1153,
        "SizeOnDisk": 1153,
        "OffsetInFile": "0x7D3C"
      }
    }
  },
  {
    "Type": "StaticMesh",
    "Name": "sm_brick_04",
    "Properties": {
      "MinLOD": {
        "bCooked": true,
        "Default": 0,
        "Value": 0
      },
      "StaticMaterials": [
        {
          "MaterialInterface": {
            "ObjectName": "MaterialInstanceConstant M_Master_Inst18",
            "ObjectPath": "DeadByDaylight/Content/Netease/Material/VertexPaint/Wall/M_Master_Inst18.0"
          },
          "MaterialSlotName": "M_Master_Inst18",
          "ImportedMaterialSlotName": "M_Master_Inst18",
          "UVChannelData": {
            "bInitialized": true,
            "bOverrideDensities": false,
            "LocalUVDensities": 265.6486,
            "LocalUVDensities": 24.00393,
            "LocalUVDensities": 0.0,
            "LocalUVDensities": 0.0
          }
        }
      ],
      "LightmapUVDensity": 24.00393,
      "LightMapResolution": 32,
      "LightMapCoordinateIndex": 1,
      "ExtendedBounds": {
        "Origin": {
          "X": 4.2915344E-06,
          "Y": 4.7683716E-07,
          "Z": 2.5467927
        },
        "BoxExtent": {
          "X": 5.754152,
          "Y": 5.1444135,
          "Z": 2.6617372
        },
        "SphereRadius": 8.095319
      }
    },
    "BodySetup": {
      "ObjectName": "BodySetup sm_brick_04:BodySetup_278",
      "ObjectPath": "DeadByDaylight/Content/Netease/Mesh/sm_brick_04.0"
    },
    "NavCollision": {
      "ObjectName": "NavCollision sm_brick_04:NavCollision_9",
      "ObjectPath": "DeadByDaylight/Content/Netease/Mesh/sm_brick_04.1"
    },
    "LightingGuid": "B4816C54-49804E65-3D2F5DAE-B21E4A08",
    "RenderData": null
  }
]