[
  {
    "Type": "Texture2D",
    "Name": "Season_48off",
    "Properties": {
      "ImportedSize": {
        "X": 138,
        "Y": 62
      },
      "LightingGuid": "C2E0127B-4F64FB12-070ACA80-C74D065E",
      "LODGroup": "TEXTUREGROUP_UI",
      "NeverStream": true
    },
    "SizeX": 138,
    "SizeY": 62,
    "PackedData": 1,
    "PixelFormat": "PF_B8G8R8A8",
    "FirstMipToSerialize": 0,
    "Mips": [
      {
        "BulkData": {
          "BulkDataFlags": "BULKDATA_ForceInlinePayload",
          "ElementCount": 34224,
          "SizeOnDisk": 34224,
          "OffsetInFile": "0x8EB0"
        },
        "SizeX": 138,
        "SizeY": 62,
        "SizeZ": 1
      }
    ]
  }
]