[
  {
    "Type": "Texture2D",
    "Name": "Season_Btn3-2",
    "Properties": {
      "ImportedSize": {
        "X": 393,
        "Y": 155
      },
      "LightingGuid": "7F278690-44244E8C-F167BCAC-A4E0E2B4",
      "LODGroup": "TEXTUREGROUP_UI",
      "NeverStream": true
    },
    "SizeX": 393,
    "SizeY": 155,
    "PackedData": 1,
    "PixelFormat": "PF_B8G8R8A8",
    "FirstMipToSerialize": 0,
    "Mips": [
      {
        "BulkData": {
          "BulkDataFlags": "BULKDATA_ForceInlinePayload",
          "ElementCount": 243660,
          "SizeOnDisk": 243660,
          "OffsetInFile": "0x3C0D0"
        },
        "SizeX": 393,
        "SizeY": 155,
        "SizeZ": 1
      }
    ]
  }
]