[
  {
    "Type": "Function",
    "Name": "ExecuteUbergraph_NE_CustomGame_PyWBP_SelectMapScreen",
    "Outer": "NE_CustomGame_PyWBP_SelectMapScreen_C",
    "ChildProperties": [
      {
        "Type": "IntProperty",
        "Name": "EntryPoint",
        "Flags": 1,
        "ElementSize": 4,
        "PropertyFlags": 148
      },
      {
        "Type": "ObjectProperty",
        "Name": "K2Node_CustomEvent_Tumbnail",
        "Flags": 1,
        "ElementSize": 8,
        "PropertyFlags": 524288,
        "PropertyClass": {
          "ObjectName": "Class PyUserWidget",
          "ObjectPath": "/Script/UnrealEnginePython"
        }
      },
      {
        "Type": "IntProperty",
        "Name": "K2Node_CustomEvent_Row",
        "Flags": 1,
        "ElementSize": 4
      },
      {
        "Type": "IntProperty",
        "Name": "K2Node_CustomEvent_Col",
        "Flags": 1,
        "ElementSize": 4
      },
      {
        "Type": "ObjectProperty",
        "Name": "CallFunc_SlotAsUniformGridSlot_ReturnValue",
        "Flags": 1,
        "ElementSize": 8,
        "PropertyFlags": 524288,
        "PropertyClass": {
          "ObjectName": "Class UniformGridSlot",
          "ObjectPath": "/Script/UMG"
        }
      }
    ],
    "FunctionFlags": 32769
  },
  {
    "Type": "Function",
    "Name": "SetTumbnailLocation",
    "Outer": "NE_CustomGame_PyWBP_SelectMapScreen_C",
    "ChildProperties": [
      {
        "Type": "ObjectProperty",
        "Name": "Tumbnail",
        "Flags": 1,
        "ElementSize": 8,
        "PropertyFlags": 524436,
        "PropertyClass": {
          "ObjectName": "Class PyUserWidget",
          "ObjectPath": "/Script/UnrealEnginePython"
        }
      },
      {
        "Type": "IntProperty",
        "Name": "Row",
        "Flags": 1,
        "ElementSize": 4,
        "PropertyFlags": 148
      },
      {
        "Type": "IntProperty",
        "Name": "Col",
        "Flags": 1,
        "ElementSize": 4,
        "PropertyFlags": 148
      }
    ],
    "FunctionFlags": 201326592
  },
  {
    "Type": "WidgetBlueprintGeneratedClass",
    "Name": "NE_CustomGame_PyWBP_SelectMapScreen_C",
    "Properties": {
      "WidgetTree": {
        "ObjectName": "WidgetTree NE_CustomGame_PyWBP_SelectMapScreen_C:WidgetTree",
        "ObjectPath": "DeadByDaylight/Content/Netease/Blueprint/UI/Mobile/GameModes/CustomGame/NE_CustomGame_PyWBP_SelectMapScreen.59"
      },
      "bAllowTemplate": true,
      "bValidTemplate": true,
      "bClassRequiresNativeTick": true,
      "TemplateAsset": {
        "AssetPathName": "/Game/Netease/Blueprint/UI/Mobile/GameModes/CustomGame/NE_CustomGame_PyWBP_SelectMapScreen.WidgetArchetype",
        "SubPathString": ""
      },
      "UberGraphFunction": {
        "ObjectName": "Function NE_CustomGame_PyWBP_SelectMapScreen_C:ExecuteUbergraph_NE_CustomGame_PyWBP_SelectMapScreen",
        "ObjectPath": "DeadByDaylight/Content/Netease/Blueprint/UI/Mobile/GameModes/CustomGame/NE_CustomGame_PyWBP_SelectMapScreen.0"
      }
    },
    "SuperStruct": {
      "ObjectName": "Class PyUserWidget",
      "ObjectPath": "/Script/UnrealEnginePython"
    },
    "Children": [
      {
        "ObjectName": "Function NE_CustomGame_PyWBP_SelectMapScreen_C:SetTumbnailLocation",
        "ObjectPath": "DeadByDaylight/Content/Netease/Blueprint/UI/Mobile/GameModes/CustomGame/NE_CustomGame_PyWBP_SelectMapScreen.1"
      },
      {
        "ObjectName": "Function NE_CustomGame_PyWBP_SelectMapScreen_C:ExecuteUbergraph_NE_CustomGame_PyWBP_SelectMapScreen",
        "ObjectPath": "DeadByDaylight/Content/Netease/Blueprint/UI/Mobile/GameModes/CustomGame/NE_CustomGame_PyWBP_SelectMapScreen.0"
      }
    ],
    "ChildProperties": [
      {
        "Type": "StructProperty",
        "Name": "UberGraphFrame",
        "Flags": 2097153,
        "ElementSize": 16,
        "PropertyFlags": 2105344,
        "Struct": {
          "ObjectName": "ScriptStruct PointerToUberGraphFrame",
          "ObjectPath": "/Script/Engine"
        }
      },
      {
        "Type": "ObjectProperty",
        "Name": "Background",
        "Flags": 2097153,
        "ElementSize": 8,
        "PropertyFlags": 562952101429260,
        "PropertyClass": {
          "ObjectName": "Class Image",
          "ObjectPath": "/Script/UMG"
        }
      },
      {
        "Type": "ObjectProperty",
        "Name": "BG",
        "Flags": 2097153,
        "ElementSize": 8,
        "PropertyFlags": 562952101429260,
        "PropertyClass": {
          "ObjectName": "Class Image",
          "ObjectPath": "/Script/UMG"
        }
      },
      {
        "Type": "ObjectProperty",
        "Name": "CloseButton",
        "Flags": 2097153,
        "ElementSize": 8,
        "PropertyFlags": 562952101429260,
        "PropertyClass": {
          "ObjectName": "Class Button",
          "ObjectPath": "/Script/UMG"
        }
      },
      {
        "Type": "ObjectProperty",
        "Name": "ContainerPanel",
        "Flags": 2097153,
        "ElementSize": 8,
        "PropertyFlags": 562952101429260,
        "PropertyClass": {
          "ObjectName": "Class CanvasPanel",
          "ObjectPath": "/Script/UMG"
        }
      },
      {
        "Type": "ObjectProperty",
        "Name": "Line",
        "Flags": 2097153,
        "ElementSize": 8,
        "PropertyFlags": 562952101429260,
        "PropertyClass": {
          "ObjectName": "Class Image",
          "ObjectPath": "/Script/UMG"
        }
      },
      {
        "Type": "ObjectProperty",
        "Name": "TitleLabel",
        "Flags": 2097153,
        "ElementSize": 8,
        "PropertyFlags": 562952101429260,
        "PropertyClass": {
          "ObjectName": "Class TextBlock",
          "ObjectPath": "/Script/UMG"
        }
      }
    ],
    "FuncMap": {
      "ExecuteUbergraph_NE_CustomGame_PyWBP_SelectMapScreen": {
        "ObjectName": "Function NE_CustomGame_PyWBP_SelectMapScreen_C:ExecuteUbergraph_NE_CustomGame_PyWBP_SelectMapScreen",
        "ObjectPath": "DeadByDaylight/Content/Netease/Blueprint/UI/Mobile/GameModes/CustomGame/NE_CustomGame_PyWBP_SelectMapScreen.0"
      },
      "SetTumbnailLocation": {
        "ObjectName": "Function NE_CustomGame_PyWBP_SelectMapScreen_C:SetTumbnailLocation",
        "ObjectPath": "DeadByDaylight/Content/Netease/Blueprint/UI/Mobile/GameModes/CustomGame/NE_CustomGame_PyWBP_SelectMapScreen.1"
      }
    },
    "ClassFlags": 10754064,
    "ClassWithin": {
      "ObjectName": "Class Object",
      "ObjectPath": "/Script/CoreUObject"
    },
    "ClassConfigName": "Engine",
    "bCooked": true,
    "ClassDefaultObject": {
      "ObjectName": "NE_CustomGame_PyWBP_SelectMapScreen_C Default__NE_CustomGame_PyWBP_SelectMapScreen_C",
      "ObjectPath": "DeadByDaylight/Content/Netease/Blueprint/UI/Mobile/GameModes/CustomGame/NE_CustomGame_PyWBP_SelectMapScreen.3"
    }
  },
  {
    "Type": "NE_CustomGame_PyWBP_SelectMapScreen_C",
    "Name": "Default__NE_CustomGame_PyWBP_SelectMapScreen_C",
    "Properties": {
      "UberGraphFrame": {},
      "PythonModule": "ui.party.party_map_selector",
      "PythonClass": "PartyMapSelectorUI",
      "bHasScriptImplementedTick": false,
      "bHasScriptImplementedPaint": false
    }
  },
  {
    "Type": "Button",
    "Name": "CloseButton",
    "Outer": "WidgetTree",
    "Properties": {
      "WidgetStyle": {
        "Normal": {
          "ImageSize": {
            "X": 73.0,
            "Y": 70.0
          },
          "TintColor": {
            "SpecifiedColor": {
              "R": 1.0,
              "G": 1.0,
              "B": 1.0,
              "A": 0.0,
              "Hex": "FFFFFF"
            }
          }
        },
        "Hovered": {
          "ImageSize": {
            "X": 73.0,
            "Y": 70.0
          },
          "TintColor": {
            "SpecifiedColor": {
              "R": 1.0,
              "G": 1.0,
              "B": 1.0,
              "A": 0.0,
              "Hex": "FFFFFF"
            }
          }
        },
        "Pressed": {
          "ImageSize": {
            "X": 73.0,
            "Y": 70.0
          },
          "TintColor": {
            "SpecifiedColor": {
              "R": 1.0,
              "G": 1.0,
              "B": 1.0,
              "A": 0.0,
              "Hex": "FFFFFF"
            }
          }
        }
      },
      "Slot": {
        "ObjectName": "CanvasPanelSlot NE_CustomGame_PyWBP_SelectMapScreen_C:WidgetTree.CanvasPanel_0.CanvasPanelSlot_0",
        "ObjectPath": "DeadByDaylight/Content/Netease/Blueprint/UI/Mobile/GameModes/CustomGame/NE_CustomGame_PyWBP_SelectMapScreen.14"
      }
    }
  },
  {
    "Type": "Button",
    "Name": "CloseButton",
    "Outer": "WidgetTree_0",
    "Properties": {
      "WidgetStyle": {
        "Normal": {
          "ImageSize": {
            "X": 73.0,
            "Y": 70.0
          },
          "TintColor": {
            "SpecifiedColor": {
              "R": 1.0,
              "G": 1.0,
              "B": 1.0,
              "A": 0.0,
              "Hex": "FFFFFF"
            }
          }
        },
        "Hovered": {
          "ImageSize": {
            "X": 73.0,
            "Y": 70.0
          },
          "TintColor": {
            "SpecifiedColor": {
              "R": 1.0,
              "G": 1.0,
              "B": 1.0,
              "A": 0.0,
              "Hex": "FFFFFF"
            }
          }
        },
        "Pressed": {
          "ImageSize": {
            "X": 73.0,
            "Y": 70.0
          },
          "TintColor": {
            "SpecifiedColor": {
              "R": 1.0,
              "G": 1.0,
              "B": 1.0,
              "A": 0.0,
              "Hex": "FFFFFF"
            }
          }
        }
      },
      "Slot": {
        "ObjectName": "CanvasPanelSlot WidgetArchetype:WidgetTree_0.CanvasPanel_0.CanvasPanelSlot_0",
        "ObjectPath": "DeadByDaylight/Content/Netease/Blueprint/UI/Mobile/GameModes/CustomGame/NE_CustomGame_PyWBP_SelectMapScreen.21"
      }
    }
  },
  {
    "Type": "CanvasPanel",
    "Name": "CanvasPanel_0",
    "Outer": "WidgetTree",
    "Properties": {
      "Slots": [
        {
          "ObjectName": "CanvasPanelSlot NE_CustomGame_PyWBP_SelectMapScreen_C:WidgetTree.CanvasPanel_0.CanvasPanelSlot_4",
          "ObjectPath": "DeadByDaylight/Content/Netease/Blueprint/UI/Mobile/GameModes/CustomGame/NE_CustomGame_PyWBP_SelectMapScreen.16"
        },
        {
          "ObjectName": "CanvasPanelSlot NE_CustomGame_PyWBP_SelectMapScreen_C:WidgetTree.CanvasPanel_0.CanvasPanelSlot_0",
          "ObjectPath": "DeadByDaylight/Content/Netease/Blueprint/UI/Mobile/GameModes/CustomGame/NE_CustomGame_PyWBP_SelectMapScreen.14"
        },
        {
          "ObjectName": "CanvasPanelSlot NE_CustomGame_PyWBP_SelectMapScreen_C:WidgetTree.CanvasPanel_0.CanvasPanelSlot_3",
          "ObjectPath": "DeadByDaylight/Content/Netease/Blueprint/UI/Mobile/GameModes/CustomGame/NE_CustomGame_PyWBP_SelectMapScreen.15"
        }
      ]
    }
  },
  {
    "Type": "CanvasPanel",
    "Name": "ContainerPanel",
    "Outer": "WidgetTree",
    "Properties": {
      "Slot": {
        "ObjectName": "ScrollBoxSlot NE_CustomGame_PyWBP_SelectMapScreen_C:WidgetTree.ScrollBox_0.ScrollBoxSlot_0",
        "ObjectPath": "DeadByDaylight/Content/Netease/Blueprint/UI/Mobile/GameModes/CustomGame/NE_CustomGame_PyWBP_SelectMapScreen.47"
      },
      "bIsVariable": true
    }
  },
  {
    "Type": "CanvasPanel",
    "Name": "Header",
    "Outer": "WidgetTree",
    "Properties": {
      "Slots": [
        {
          "ObjectName": "CanvasPanelSlot NE_CustomGame_PyWBP_SelectMapScreen_C:WidgetTree.Header.CanvasPanelSlot_2",
          "ObjectPath": "DeadByDaylight/Content/Netease/Blueprint/UI/Mobile/GameModes/CustomGame/NE_CustomGame_PyWBP_SelectMapScreen.17"
        }
      ],
      "Slot": {
        "ObjectName": "CanvasPanelSlot NE_CustomGame_PyWBP_SelectMapScreen_C:WidgetTree.SafeZone.CanvasPanelSlot_0",
        "ObjectPath": "DeadByDaylight/Content/Netease/Blueprint/UI/Mobile/GameModes/CustomGame/NE_CustomGame_PyWBP_SelectMapScreen.18"
      },
      "Clipping": "EWidgetClipping::ClipToBounds"
    }
  },
  {
    "Type": "CanvasPanel",
    "Name": "SafeZone",
    "Outer": "WidgetTree",
    "Properties": {
      "Slots": [
        {
          "ObjectName": "CanvasPanelSlot NE_CustomGame_PyWBP_SelectMapScreen_C:WidgetTree.SafeZone.CanvasPanelSlot_0",
          "ObjectPath": "DeadByDaylight/Content/Netease/Blueprint/UI/Mobile/GameModes/CustomGame/NE_CustomGame_PyWBP_SelectMapScreen.18"
        },
        {
          "ObjectName": "CanvasPanelSlot NE_CustomGame_PyWBP_SelectMapScreen_C:WidgetTree.SafeZone.CanvasPanelSlot_4",
          "ObjectPath": "DeadByDaylight/Content/Netease/Blueprint/UI/Mobile/GameModes/CustomGame/NE_CustomGame_PyWBP_SelectMapScreen.20"
        },
        {
          "ObjectName": "CanvasPanelSlot NE_CustomGame_PyWBP_SelectMapScreen_C:WidgetTree.SafeZone.CanvasPanelSlot_3",
          "ObjectPath": "DeadByDaylight/Content/Netease/Blueprint/UI/Mobile/GameModes/CustomGame/NE_CustomGame_PyWBP_SelectMapScreen.19"
        }
      ],
      "Slot": {
        "ObjectName": "VerticalBoxSlot NE_CustomGame_PyWBP_SelectMapScreen_C:WidgetTree.VerticalBox_595.VerticalBoxSlot_1",
        "ObjectPath": "DeadByDaylight/Content/Netease/Blueprint/UI/Mobile/GameModes/CustomGame/NE_CustomGame_PyWBP_SelectMapScreen.56"
      }
    }
  },
  {
    "Type": "CanvasPanel",
    "Name": "CanvasPanel_0",
    "Outer": "WidgetTree_0",
    "Properties": {
      "Slots": [
        {
          "ObjectName": "CanvasPanelSlot WidgetArchetype:WidgetTree_0.CanvasPanel_0.CanvasPanelSlot_4",
          "ObjectPath": "DeadByDaylight/Content/Netease/Blueprint/UI/Mobile/GameModes/CustomGame/NE_CustomGame_PyWBP_SelectMapScreen.23"
        },
        {
          "ObjectName": "CanvasPanelSlot WidgetArchetype:WidgetTree_0.CanvasPanel_0.CanvasPanelSlot_0",
          "ObjectPath": "DeadByDaylight/Content/Netease/Blueprint/UI/Mobile/GameModes/CustomGame/NE_CustomGame_PyWBP_SelectMapScreen.21"
        },
        {
          "ObjectName": "CanvasPanelSlot WidgetArchetype:WidgetTree_0.CanvasPanel_0.CanvasPanelSlot_3",
          "ObjectPath": "DeadByDaylight/Content/Netease/Blueprint/UI/Mobile/GameModes/CustomGame/NE_CustomGame_PyWBP_SelectMapScreen.22"
        }
      ]
    }
  },
  {
    "Type": "CanvasPanel",
    "Name": "ContainerPanel",
    "Outer": "WidgetTree_0",
    "Properties": {
      "Slot": {
        "ObjectName": "ScrollBoxSlot WidgetArchetype:WidgetTree_0.ScrollBox_0.ScrollBoxSlot_0",
        "ObjectPath": "DeadByDaylight/Content/Netease/Blueprint/UI/Mobile/GameModes/CustomGame/NE_CustomGame_PyWBP_SelectMapScreen.48"
      },
      "bIsVariable": true
    }
  },
  {
    "Type": "CanvasPanel",
    "Name": "Header",
    "Outer": "WidgetTree_0",
    "Properties": {
      "Slots": [
        {
          "ObjectName": "CanvasPanelSlot WidgetArchetype:WidgetTree_0.Header.CanvasPanelSlot_2",
          "ObjectPath": "DeadByDaylight/Content/Netease/Blueprint/UI/Mobile/GameModes/CustomGame/NE_CustomGame_PyWBP_SelectMapScreen.24"
        }
      ],
      "Slot": {
        "ObjectName": "CanvasPanelSlot WidgetArchetype:WidgetTree_0.SafeZone.CanvasPanelSlot_0",
        "ObjectPath": "DeadByDaylight/Content/Netease/Blueprint/UI/Mobile/GameModes/CustomGame/NE_CustomGame_PyWBP_SelectMapScreen.25"
      },
      "Clipping": "EWidgetClipping::ClipToBounds"
    }
  },
  {
    "Type": "CanvasPanel",
    "Name": "SafeZone",
    "Outer": "WidgetTree_0",
    "Properties": {
      "Slots": [
        {
          "ObjectName": "CanvasPanelSlot WidgetArchetype:WidgetTree_0.SafeZone.CanvasPanelSlot_0",
          "ObjectPath": "DeadByDaylight/Content/Netease/Blueprint/UI/Mobile/GameModes/CustomGame/NE_CustomGame_PyWBP_SelectMapScreen.25"
        },
        {
          "ObjectName": "CanvasPanelSlot WidgetArchetype:WidgetTree_0.SafeZone.CanvasPanelSlot_4",
          "ObjectPath": "DeadByDaylight/Content/Netease/Blueprint/UI/Mobile/GameModes/CustomGame/NE_CustomGame_PyWBP_SelectMapScreen.27"
        },
        {
          "ObjectName": "CanvasPanelSlot WidgetArchetype:WidgetTree_0.SafeZone.CanvasPanelSlot_3",
          "ObjectPath": "DeadByDaylight/Content/Netease/Blueprint/UI/Mobile/GameModes/CustomGame/NE_CustomGame_PyWBP_SelectMapScreen.26"
        }
      ],
      "Slot": {
        "ObjectName": "VerticalBoxSlot WidgetArchetype:WidgetTree_0.VerticalBox_595.VerticalBoxSlot_1",
        "ObjectPath": "DeadByDaylight/Content/Netease/Blueprint/UI/Mobile/GameModes/CustomGame/NE_CustomGame_PyWBP_SelectMapScreen.58"
      }
    }
  },
  {
    "Type": "CanvasPanelSlot",
    "Name": "CanvasPanelSlot_0",
    "Outer": "CanvasPanel_0",
    "Properties": {
      "LayoutData": {
        "Offsets": {
          "Right": 0.0,
          "Bottom": 0.0
        },
        "Anchors": {
          "Maximum": {
            "X": 1.0,
            "Y": 1.0
          }
        }
      },
      "Parent": {
        "ObjectName": "CanvasPanel NE_CustomGame_PyWBP_SelectMapScreen_C:WidgetTree.CanvasPanel_0",
        "ObjectPath": "DeadByDaylight/Content/Netease/Blueprint/UI/Mobile/GameModes/CustomGame/NE_CustomGame_PyWBP_SelectMapScreen.6"
      },
      "Content": {
        "ObjectName": "Button NE_CustomGame_PyWBP_SelectMapScreen_C:WidgetTree.CloseButton",
        "ObjectPath": "DeadByDaylight/Content/Netease/Blueprint/UI/Mobile/GameModes/CustomGame/NE_CustomGame_PyWBP_SelectMapScreen.4"
      }
    }
  },
  {
    "Type": "CanvasPanelSlot",
    "Name": "CanvasPanelSlot_3",
    "Outer": "CanvasPanel_0",
    "Properties": {
      "LayoutData": {
        "Offsets": {
          "Left": -784.0,
          "Right": 840.0,
          "Bottom": 0.0
        },
        "Anchors": {
          "Minimum": {
            "X": 1.0,
            "Y": 0.0
          },
          "Maximum": {
            "X": 1.0,
            "Y": 1.0
          }
        }
      },
      "Parent": {
        "ObjectName": "CanvasPanel NE_CustomGame_PyWBP_SelectMapScreen_C:WidgetTree.CanvasPanel_0",
        "ObjectPath": "DeadByDaylight/Content/Netease/Blueprint/UI/Mobile/GameModes/CustomGame/NE_CustomGame_PyWBP_SelectMapScreen.6"
      },
      "Content": {
        "ObjectName": "HorizontalBox NE_CustomGame_PyWBP_SelectMapScreen_C:WidgetTree.HorizontalBox_189",
        "ObjectPath": "DeadByDaylight/Content/Netease/Blueprint/UI/Mobile/GameModes/CustomGame/NE_CustomGame_PyWBP_SelectMapScreen.29"
      }
    }
  },
  {
    "Type": "CanvasPanelSlot",
    "Name": "CanvasPanelSlot_4",
    "Outer": "CanvasPanel_0",
    "Properties": {
      "LayoutData": {
        "Offsets": {
          "Right": 890.0,
          "Bottom": 0.0
        },
        "Anchors": {
          "Minimum": {
            "X": 1.0,
            "Y": 0.0
          },
          "Maximum": {
            "X": 1.0,
            "Y": 1.0
          }
        },
        "Alignment": {
          "X": 1.0,
          "Y": 0.0
        }
      },
      "Parent": {
        "ObjectName": "CanvasPanel NE_CustomGame_PyWBP_SelectMapScreen_C:WidgetTree.CanvasPanel_0",
        "ObjectPath": "DeadByDaylight/Content/Netease/Blueprint/UI/Mobile/GameModes/CustomGame/NE_CustomGame_PyWBP_SelectMapScreen.6"
      },
      "Content": {
        "ObjectName": "HorizontalBox NE_CustomGame_PyWBP_SelectMapScreen_C:WidgetTree.HorizontalBox_117",
        "ObjectPath": "DeadByDaylight/Content/Netease/Blueprint/UI/Mobile/GameModes/CustomGame/NE_CustomGame_PyWBP_SelectMapScreen.28"
      }
    }
  },
  {
    "Type": "CanvasPanelSlot",
    "Name": "CanvasPanelSlot_2",
    "Outer": "Header",
    "Properties": {
      "LayoutData": {
        "Offsets": {
          "Right": 0.0,
          "Bottom": 184.0
        },
        "Anchors": {
          "Minimum": {
            "X": 0.0,
            "Y": 0.5
          },
          "Maximum": {
            "X": 1.0,
            "Y": 0.5
          }
        },
        "Alignment": {
          "X": 0.0,
          "Y": 0.5
        }
      },
      "bAutoSize": true,
      "Parent": {
        "ObjectName": "CanvasPanel NE_CustomGame_PyWBP_SelectMapScreen_C:WidgetTree.Header",
        "ObjectPath": "DeadByDaylight/Content/Netease/Blueprint/UI/Mobile/GameModes/CustomGame/NE_CustomGame_PyWBP_SelectMapScreen.8"
      },
      "Content": {
        "ObjectName": "VerticalBox NE_CustomGame_PyWBP_SelectMapScreen_C:WidgetTree.VerticalBox_0",
        "ObjectPath": "DeadByDaylight/Content/Netease/Blueprint/UI/Mobile/GameModes/CustomGame/NE_CustomGame_PyWBP_SelectMapScreen.51"
      }
    }
  },
  {
    "Type": "CanvasPanelSlot",
    "Name": "CanvasPanelSlot_0",
    "Outer": "SafeZone",
    "Properties": {
      "LayoutData": {
        "Offsets": {
          "Right": 0.0,
          "Bottom": 136.98022
        },
        "Anchors": {
          "Maximum": {
            "X": 1.0,
            "Y": 0.0
          }
        },
        "Alignment": {
          "X": 1.0,
          "Y": 0.0
        }
      },
      "Parent": {
        "ObjectName": "CanvasPanel NE_CustomGame_PyWBP_SelectMapScreen_C:WidgetTree.SafeZone",
        "ObjectPath": "DeadByDaylight/Content/Netease/Blueprint/UI/Mobile/GameModes/CustomGame/NE_CustomGame_PyWBP_SelectMapScreen.9"
      },
      "Content": {
        "ObjectName": "CanvasPanel NE_CustomGame_PyWBP_SelectMapScreen_C:WidgetTree.Header",
        "ObjectPath": "DeadByDaylight/Content/Netease/Blueprint/UI/Mobile/GameModes/CustomGame/NE_CustomGame_PyWBP_SelectMapScreen.8"
      }
    }
  },
  {
    "Type": "CanvasPanelSlot",
    "Name": "CanvasPanelSlot_3",
    "Outer": "SafeZone",
    "Properties": {
      "LayoutData": {
        "Offsets": {
          "Left": -799.0,
          "Top": 142.0,
          "Right": 732.0,
          "Bottom": 78.0
        },
        "Anchors": {
          "Minimum": {
            "X": 1.0,
            "Y": 0.0
          },
          "Maximum": {
            "X": 1.0,
            "Y": 1.0
          }
        }
      },
      "Parent": {
        "ObjectName": "CanvasPanel NE_CustomGame_PyWBP_SelectMapScreen_C:WidgetTree.SafeZone",
        "ObjectPath": "DeadByDaylight/Content/Netease/Blueprint/UI/Mobile/GameModes/CustomGame/NE_CustomGame_PyWBP_SelectMapScreen.9"
      },
      "Content": {
        "ObjectName": "ScrollBox NE_CustomGame_PyWBP_SelectMapScreen_C:WidgetTree.ScrollBox_0",
        "ObjectPath": "DeadByDaylight/Content/Netease/Blueprint/UI/Mobile/GameModes/CustomGame/NE_CustomGame_PyWBP_SelectMapScreen.45"
      }
    }
  },
  {
    "Type": "CanvasPanelSlot",
    "Name": "CanvasPanelSlot_4",
    "Outer": "SafeZone",
    "Properties": {
      "LayoutData": {
        "Offsets": {
          "Left": -756.0,
          "Top": 103.0,
          "Right": 695.0,
          "Bottom": 3.0
        },
        "Anchors": {
          "Minimum": {
            "X": 1.0,
            "Y": 0.0
          },
          "Maximum": {
            "X": 1.0,
            "Y": 0.0
          }
        }
      },
      "Parent": {
        "ObjectName": "CanvasPanel NE_CustomGame_PyWBP_SelectMapScreen_C:WidgetTree.SafeZone",
        "ObjectPath": "DeadByDaylight/Content/Netease/Blueprint/UI/Mobile/GameModes/CustomGame/NE_CustomGame_PyWBP_SelectMapScreen.9"
      },
      "Content": {
        "ObjectName": "Image NE_CustomGame_PyWBP_SelectMapScreen_C:WidgetTree.Line",
        "ObjectPath": "DeadByDaylight/Content/Netease/Blueprint/UI/Mobile/GameModes/CustomGame/NE_CustomGame_PyWBP_SelectMapScreen.40"
      }
    }
  },
  {
    "Type": "CanvasPanelSlot",
    "Name": "CanvasPanelSlot_0",
    "Outer": "CanvasPanel_0",
    "Properties": {
      "LayoutData": {
        "Offsets": {
          "Right": 0.0,
          "Bottom": 0.0
        },
        "Anchors": {
          "Maximum": {
            "X": 1.0,
            "Y": 1.0
          }
        }
      },
      "Parent": {
        "ObjectName": "CanvasPanel WidgetArchetype:WidgetTree_0.CanvasPanel_0",
        "ObjectPath": "DeadByDaylight/Content/Netease/Blueprint/UI/Mobile/GameModes/CustomGame/NE_CustomGame_PyWBP_SelectMapScreen.10"
      },
      "Content": {
        "ObjectName": "Button WidgetArchetype:WidgetTree_0.CloseButton",
        "ObjectPath": "DeadByDaylight/Content/Netease/Blueprint/UI/Mobile/GameModes/CustomGame/NE_CustomGame_PyWBP_SelectMapScreen.5"
      }
    }
  },
  {
    "Type": "CanvasPanelSlot",
    "Name": "CanvasPanelSlot_3",
    "Outer": "CanvasPanel_0",
    "Properties": {
      "LayoutData": {
        "Offsets": {
          "Left": -784.0,
          "Right": 840.0,
          "Bottom": 0.0
        },
        "Anchors": {
          "Minimum": {
            "X": 1.0,
            "Y": 0.0
          },
          "Maximum": {
            "X": 1.0,
            "Y": 1.0
          }
        }
      },
      "Parent": {
        "ObjectName": "CanvasPanel WidgetArchetype:WidgetTree_0.CanvasPanel_0",
        "ObjectPath": "DeadByDaylight/Content/Netease/Blueprint/UI/Mobile/GameModes/CustomGame/NE_CustomGame_PyWBP_SelectMapScreen.10"
      },
      "Content": {
        "ObjectName": "HorizontalBox WidgetArchetype:WidgetTree_0.HorizontalBox_189",
        "ObjectPath": "DeadByDaylight/Content/Netease/Blueprint/UI/Mobile/GameModes/CustomGame/NE_CustomGame_PyWBP_SelectMapScreen.31"
      }
    }
  },
  {
    "Type": "CanvasPanelSlot",
    "Name": "CanvasPanelSlot_4",
    "Outer": "CanvasPanel_0",
    "Properties": {
      "LayoutData": {
        "Offsets": {
          "Right": 890.0,
          "Bottom": 0.0
        },
        "Anchors": {
          "Minimum": {
            "X": 1.0,
            "Y": 0.0
          },
          "Maximum": {
            "X": 1.0,
            "Y": 1.0
          }
        },
        "Alignment": {
          "X": 1.0,
          "Y": 0.0
        }
      },
      "Parent": {
        "ObjectName": "CanvasPanel WidgetArchetype:WidgetTree_0.CanvasPanel_0",
        "ObjectPath": "DeadByDaylight/Content/Netease/Blueprint/UI/Mobile/GameModes/CustomGame/NE_CustomGame_PyWBP_SelectMapScreen.10"
      },
      "Content": {
        "ObjectName": "HorizontalBox WidgetArchetype:WidgetTree_0.HorizontalBox_117",
        "ObjectPath": "DeadByDaylight/Content/Netease/Blueprint/UI/Mobile/GameModes/CustomGame/NE_CustomGame_PyWBP_SelectMapScreen.30"
      }
    }
  },
  {
    "Type": "CanvasPanelSlot",
    "Name": "CanvasPanelSlot_2",
    "Outer": "Header",
    "Properties": {
      "LayoutData": {
        "Offsets": {
          "Right": 0.0,
          "Bottom": 184.0
        },
        "Anchors": {
          "Minimum": {
            "X": 0.0,
            "Y": 0.5
          },
          "Maximum": {
            "X": 1.0,
            "Y": 0.5
          }
        },
        "Alignment": {
          "X": 0.0,
          "Y": 0.5
        }
      },
      "bAutoSize": true,
      "Parent": {
        "ObjectName": "CanvasPanel WidgetArchetype:WidgetTree_0.Header",
        "ObjectPath": "DeadByDaylight/Content/Netease/Blueprint/UI/Mobile/GameModes/CustomGame/NE_CustomGame_PyWBP_SelectMapScreen.12"
      },
      "Content": {
        "ObjectName": "VerticalBox WidgetArchetype:WidgetTree_0.VerticalBox_0",
        "ObjectPath": "DeadByDaylight/Content/Netease/Blueprint/UI/Mobile/GameModes/CustomGame/NE_CustomGame_PyWBP_SelectMapScreen.53"
      }
    }
  },
  {
    "Type": "CanvasPanelSlot",
    "Name": "CanvasPanelSlot_0",
    "Outer": "SafeZone",
    "Properties": {
      "LayoutData": {
        "Offsets": {
          "Right": 0.0,
          "Bottom": 136.98022
        },
        "Anchors": {
          "Maximum": {
            "X": 1.0,
            "Y": 0.0
          }
        },
        "Alignment": {
          "X": 1.0,
          "Y": 0.0
        }
      },
      "Parent": {
        "ObjectName": "CanvasPanel WidgetArchetype:WidgetTree_0.SafeZone",
        "ObjectPath": "DeadByDaylight/Content/Netease/Blueprint/UI/Mobile/GameModes/CustomGame/NE_CustomGame_PyWBP_SelectMapScreen.13"
      },
      "Content": {
        "ObjectName": "CanvasPanel WidgetArchetype:WidgetTree_0.Header",
        "ObjectPath": "DeadByDaylight/Content/Netease/Blueprint/UI/Mobile/GameModes/CustomGame/NE_CustomGame_PyWBP_SelectMapScreen.12"
      }
    }
  },
  {
    "Type": "CanvasPanelSlot",
    "Name": "CanvasPanelSlot_3",
    "Outer": "SafeZone",
    "Properties": {
      "LayoutData": {
        "Offsets": {
          "Left": -799.0,
          "Top": 142.0,
          "Right": 732.0,
          "Bottom": 78.0
        },
        "Anchors": {
          "Minimum": {
            "X": 1.0,
            "Y": 0.0
          },
          "Maximum": {
            "X": 1.0,
            "Y": 1.0
          }
        }
      },
      "Parent": {
        "ObjectName": "CanvasPanel WidgetArchetype:WidgetTree_0.SafeZone",
        "ObjectPath": "DeadByDaylight/Content/Netease/Blueprint/UI/Mobile/GameModes/CustomGame/NE_CustomGame_PyWBP_SelectMapScreen.13"
      },
      "Content": {
        "ObjectName": "ScrollBox WidgetArchetype:WidgetTree_0.ScrollBox_0",
        "ObjectPath": "DeadByDaylight/Content/Netease/Blueprint/UI/Mobile/GameModes/CustomGame/NE_CustomGame_PyWBP_SelectMapScreen.46"
      }
    }
  },
  {
    "Type": "CanvasPanelSlot",
    "Name": "CanvasPanelSlot_4",
    "Outer": "SafeZone",
    "Properties": {
      "LayoutData": {
        "Offsets": {
          "Left": -756.0,
          "Top": 103.0,
          "Right": 695.0,
          "Bottom": 3.0
        },
        "Anchors": {
          "Minimum": {
            "X": 1.0,
            "Y": 0.0
          },
          "Maximum": {
            "X": 1.0,
            "Y": 0.0
          }
        }
      },
      "Parent": {
        "ObjectName": "CanvasPanel WidgetArchetype:WidgetTree_0.SafeZone",
        "ObjectPath": "DeadByDaylight/Content/Netease/Blueprint/UI/Mobile/GameModes/CustomGame/NE_CustomGame_PyWBP_SelectMapScreen.13"
      },
      "Content": {
        "ObjectName": "Image WidgetArchetype:WidgetTree_0.Line",
        "ObjectPath": "DeadByDaylight/Content/Netease/Blueprint/UI/Mobile/GameModes/CustomGame/NE_CustomGame_PyWBP_SelectMapScreen.43"
      }
    }
  },
  {
    "Type": "HorizontalBox",
    "Name": "HorizontalBox_117",
    "Outer": "WidgetTree",
    "Properties": {
      "Slots": [
        {
          "ObjectName": "HorizontalBoxSlot NE_CustomGame_PyWBP_SelectMapScreen_C:WidgetTree.HorizontalBox_117.HorizontalBoxSlot_2",
          "ObjectPath": "DeadByDaylight/Content/Netease/Blueprint/UI/Mobile/GameModes/CustomGame/NE_CustomGame_PyWBP_SelectMapScreen.33"
        },
        {
          "ObjectName": "HorizontalBoxSlot NE_CustomGame_PyWBP_SelectMapScreen_C:WidgetTree.HorizontalBox_117.HorizontalBoxSlot_0",
          "ObjectPath": "DeadByDaylight/Content/Netease/Blueprint/UI/Mobile/GameModes/CustomGame/NE_CustomGame_PyWBP_SelectMapScreen.32"
        }
      ],
      "Slot": {
        "ObjectName": "CanvasPanelSlot NE_CustomGame_PyWBP_SelectMapScreen_C:WidgetTree.CanvasPanel_0.CanvasPanelSlot_4",
        "ObjectPath": "DeadByDaylight/Content/Netease/Blueprint/UI/Mobile/GameModes/CustomGame/NE_CustomGame_PyWBP_SelectMapScreen.16"
      }
    }
  },
  {
    "Type": "HorizontalBox",
    "Name": "HorizontalBox_189",
    "Outer": "WidgetTree",
    "Properties": {
      "Slots": [
        {
          "ObjectName": "HorizontalBoxSlot NE_CustomGame_PyWBP_SelectMapScreen_C:WidgetTree.HorizontalBox_189.HorizontalBoxSlot_0",
          "ObjectPath": "DeadByDaylight/Content/Netease/Blueprint/UI/Mobile/GameModes/CustomGame/NE_CustomGame_PyWBP_SelectMapScreen.34"
        }
      ],
      "Slot": {
        "ObjectName": "CanvasPanelSlot NE_CustomGame_PyWBP_SelectMapScreen_C:WidgetTree.CanvasPanel_0.CanvasPanelSlot_3",
        "ObjectPath": "DeadByDaylight/Content/Netease/Blueprint/UI/Mobile/GameModes/CustomGame/NE_CustomGame_PyWBP_SelectMapScreen.15"
      }
    }
  },
  {
    "Type": "HorizontalBox",
    "Name": "HorizontalBox_117",
    "Outer": "WidgetTree_0",
    "Properties": {
      "Slots": [
        {
          "ObjectName": "HorizontalBoxSlot WidgetArchetype:WidgetTree_0.HorizontalBox_117.HorizontalBoxSlot_2",
          "ObjectPath": "DeadByDaylight/Content/Netease/Blueprint/UI/Mobile/GameModes/CustomGame/NE_CustomGame_PyWBP_SelectMapScreen.36"
        },
        {
          "ObjectName": "HorizontalBoxSlot WidgetArchetype:WidgetTree_0.HorizontalBox_117.HorizontalBoxSlot_0",
          "ObjectPath": "DeadByDaylight/Content/Netease/Blueprint/UI/Mobile/GameModes/CustomGame/NE_CustomGame_PyWBP_SelectMapScreen.35"
        }
      ],
      "Slot": {
        "ObjectName": "CanvasPanelSlot WidgetArchetype:WidgetTree_0.CanvasPanel_0.CanvasPanelSlot_4",
        "ObjectPath": "DeadByDaylight/Content/Netease/Blueprint/UI/Mobile/GameModes/CustomGame/NE_CustomGame_PyWBP_SelectMapScreen.23"
      }
    }
  },
  {
    "Type": "HorizontalBox",
    "Name": "HorizontalBox_189",
    "Outer": "WidgetTree_0",
    "Properties": {
      "Slots": [
        {
          "ObjectName": "HorizontalBoxSlot WidgetArchetype:WidgetTree_0.HorizontalBox_189.HorizontalBoxSlot_0",
          "ObjectPath": "DeadByDaylight/Content/Netease/Blueprint/UI/Mobile/GameModes/CustomGame/NE_CustomGame_PyWBP_SelectMapScreen.37"
        }
      ],
      "Slot": {
        "ObjectName": "CanvasPanelSlot WidgetArchetype:WidgetTree_0.CanvasPanel_0.CanvasPanelSlot_3",
        "ObjectPath": "DeadByDaylight/Content/Netease/Blueprint/UI/Mobile/GameModes/CustomGame/NE_CustomGame_PyWBP_SelectMapScreen.22"
      }
    }
  },
  {
    "Type": "HorizontalBoxSlot",
    "Name": "HorizontalBoxSlot_0",
    "Outer": "HorizontalBox_117",
    "Properties": {
      "Size": {
        "SizeRule": "ESlateSizeRule::Fill"
      },
      "Parent": {
        "ObjectName": "HorizontalBox NE_CustomGame_PyWBP_SelectMapScreen_C:WidgetTree.HorizontalBox_117",
        "ObjectPath": "DeadByDaylight/Content/Netease/Blueprint/UI/Mobile/GameModes/CustomGame/NE_CustomGame_PyWBP_SelectMapScreen.28"
      },
      "Content": {
        "ObjectName": "Image NE_CustomGame_PyWBP_SelectMapScreen_C:WidgetTree.BG",
        "ObjectPath": "DeadByDaylight/Content/Netease/Blueprint/UI/Mobile/GameModes/CustomGame/NE_CustomGame_PyWBP_SelectMapScreen.39"
      }
    }
  },
  {
    "Type": "HorizontalBoxSlot",
    "Name": "HorizontalBoxSlot_2",
    "Outer": "HorizontalBox_117",
    "Properties": {
      "Parent": {
        "ObjectName": "HorizontalBox NE_CustomGame_PyWBP_SelectMapScreen_C:WidgetTree.HorizontalBox_117",
        "ObjectPath": "DeadByDaylight/Content/Netease/Blueprint/UI/Mobile/GameModes/CustomGame/NE_CustomGame_PyWBP_SelectMapScreen.28"
      },
      "Content": {
        "ObjectName": "Image NE_CustomGame_PyWBP_SelectMapScreen_C:WidgetTree.Background",
        "ObjectPath": "DeadByDaylight/Content/Netease/Blueprint/UI/Mobile/GameModes/CustomGame/NE_CustomGame_PyWBP_SelectMapScreen.38"
      }
    }
  },
  {
    "Type": "HorizontalBoxSlot",
    "Name": "HorizontalBoxSlot_0",
    "Outer": "HorizontalBox_189",
    "Properties": {
      "Size": {
        "SizeRule": "ESlateSizeRule::Fill"
      },
      "Parent": {
        "ObjectName": "HorizontalBox NE_CustomGame_PyWBP_SelectMapScreen_C:WidgetTree.HorizontalBox_189",
        "ObjectPath": "DeadByDaylight/Content/Netease/Blueprint/UI/Mobile/GameModes/CustomGame/NE_CustomGame_PyWBP_SelectMapScreen.29"
      },
      "Content": {
        "ObjectName": "VerticalBox NE_CustomGame_PyWBP_SelectMapScreen_C:WidgetTree.VerticalBox_595",
        "ObjectPath": "DeadByDaylight/Content/Netease/Blueprint/UI/Mobile/GameModes/CustomGame/NE_CustomGame_PyWBP_SelectMapScreen.52"
      }
    }
  },
  {
    "Type": "HorizontalBoxSlot",
    "Name": "HorizontalBoxSlot_0",
    "Outer": "HorizontalBox_117",
    "Properties": {
      "Size": {
        "SizeRule": "ESlateSizeRule::Fill"
      },
      "Parent": {
        "ObjectName": "HorizontalBox WidgetArchetype:WidgetTree_0.HorizontalBox_117",
        "ObjectPath": "DeadByDaylight/Content/Netease/Blueprint/UI/Mobile/GameModes/CustomGame/NE_CustomGame_PyWBP_SelectMapScreen.30"
      },
      "Content": {
        "ObjectName": "Image WidgetArchetype:WidgetTree_0.BG",
        "ObjectPath": "DeadByDaylight/Content/Netease/Blueprint/UI/Mobile/GameModes/CustomGame/NE_CustomGame_PyWBP_SelectMapScreen.42"
      }
    }
  },
  {
    "Type": "HorizontalBoxSlot",
    "Name": "HorizontalBoxSlot_2",
    "Outer": "HorizontalBox_117",
    "Properties": {
      "Parent": {
        "ObjectName": "HorizontalBox WidgetArchetype:WidgetTree_0.HorizontalBox_117",
        "ObjectPath": "DeadByDaylight/Content/Netease/Blueprint/UI/Mobile/GameModes/CustomGame/NE_CustomGame_PyWBP_SelectMapScreen.30"
      },
      "Content": {
        "ObjectName": "Image WidgetArchetype:WidgetTree_0.Background",
        "ObjectPath": "DeadByDaylight/Content/Netease/Blueprint/UI/Mobile/GameModes/CustomGame/NE_CustomGame_PyWBP_SelectMapScreen.41"
      }
    }
  },
  {
    "Type": "HorizontalBoxSlot",
    "Name": "HorizontalBoxSlot_0",
    "Outer": "HorizontalBox_189",
    "Properties": {
      "Size": {
        "SizeRule": "ESlateSizeRule::Fill"
      },
      "Parent": {
        "ObjectName": "HorizontalBox WidgetArchetype:WidgetTree_0.HorizontalBox_189",
        "ObjectPath": "DeadByDaylight/Content/Netease/Blueprint/UI/Mobile/GameModes/CustomGame/NE_CustomGame_PyWBP_SelectMapScreen.31"
      },
      "Content": {
        "ObjectName": "VerticalBox WidgetArchetype:WidgetTree_0.VerticalBox_595",
        "ObjectPath": "DeadByDaylight/Content/Netease/Blueprint/UI/Mobile/GameModes/CustomGame/NE_CustomGame_PyWBP_SelectMapScreen.54"
      }
    }
  },
  {
    "Type": "Image",
    "Name": "Background",
    "Outer": "WidgetTree",
    "Properties": {
      "Brush": {
        "ImageSize": {
          "X": 210.0,
          "Y": 1013.0
        },
        "Margin": {
          "Right": 0.697248
        },
        "ResourceObject": {
          "ObjectName": "PaperSprite Atl_Tooltip_bg_png",
          "ObjectPath": "DeadByDaylight/Content/UI/UMGAssets/Tooltips/OutputPaper2D/Frames/Atl_Tooltip_bg_png.1"
        },
        "DrawAs": "ESlateBrushDrawType::Box"
      },
      "Slot": {
        "ObjectName": "HorizontalBoxSlot NE_CustomGame_PyWBP_SelectMapScreen_C:WidgetTree.HorizontalBox_117.HorizontalBoxSlot_2",
        "ObjectPath": "DeadByDaylight/Content/Netease/Blueprint/UI/Mobile/GameModes/CustomGame/NE_CustomGame_PyWBP_SelectMapScreen.33"
      },
      "RenderTransform": {
        "Scale": {
          "X": -1.0,
          "Y": 1.0
        }
      }
    }
  },
  {
    "Type": "Image",
    "Name": "BG",
    "Outer": "WidgetTree",
    "Properties": {
      "Brush": {
        "Margin": {
          "Left": 0.3,
          "Top": 0.3,
          "Right": 0.3,
          "Bottom": 0.3
        },
        "DrawAs": "ESlateBrushDrawType::Box"
      },
      "ColorAndOpacity": {
        "R": 0.0,
        "G": 0.0,
        "B": 0.0,
        "A": 1.0,
        "Hex": "FF000000"
      },
      "Slot": {
        "ObjectName": "HorizontalBoxSlot NE_CustomGame_PyWBP_SelectMapScreen_C:WidgetTree.HorizontalBox_117.HorizontalBoxSlot_0",
        "ObjectPath": "DeadByDaylight/Content/Netease/Blueprint/UI/Mobile/GameModes/CustomGame/NE_CustomGame_PyWBP_SelectMapScreen.32"
      }
    }
  },
  {
    "Type": "Image",
    "Name": "Line",
    "Outer": "WidgetTree",
    "Properties": {
      "Brush": {
        "ImageSize": {
          "X": 695.0,
          "Y": 3.0
        },
        "ResourceObject": {
          "ObjectName": "Texture2D GamesMode_Line_NE",
          "ObjectPath": "DeadByDaylight/Content/UI/UMGAssets/Tooltips/OutputPaper2D/Frames/GamesMode_Line_NE.0"
        }
      },
      "Slot": {
        "ObjectName": "CanvasPanelSlot NE_CustomGame_PyWBP_SelectMapScreen_C:WidgetTree.SafeZone.CanvasPanelSlot_4",
        "ObjectPath": "DeadByDaylight/Content/Netease/Blueprint/UI/Mobile/GameModes/CustomGame/NE_CustomGame_PyWBP_SelectMapScreen.20"
      }
    }
  },
  {
    "Type": "Image",
    "Name": "Background",
    "Outer": "WidgetTree_0",
    "Properties": {
      "Brush": {
        "ImageSize": {
          "X": 210.0,
          "Y": 1013.0
        },
        "Margin": {
          "Right": 0.697248
        },
        "ResourceObject": {
          "ObjectName": "PaperSprite Atl_Tooltip_bg_png",
          "ObjectPath": "DeadByDaylight/Content/UI/UMGAssets/Tooltips/OutputPaper2D/Frames/Atl_Tooltip_bg_png.1"
        },
        "DrawAs": "ESlateBrushDrawType::Box"
      },
      "Slot": {
        "ObjectName": "HorizontalBoxSlot WidgetArchetype:WidgetTree_0.HorizontalBox_117.HorizontalBoxSlot_2",
        "ObjectPath": "DeadByDaylight/Content/Netease/Blueprint/UI/Mobile/GameModes/CustomGame/NE_CustomGame_PyWBP_SelectMapScreen.36"
      },
      "RenderTransform": {
        "Scale": {
          "X": -1.0,
          "Y": 1.0
        }
      }
    }
  },
  {
    "Type": "Image",
    "Name": "BG",
    "Outer": "WidgetTree_0",
    "Properties": {
      "Brush": {
        "Margin": {
          "Left": 0.3,
          "Top": 0.3,
          "Right": 0.3,
          "Bottom": 0.3
        },
        "DrawAs": "ESlateBrushDrawType::Box"
      },
      "ColorAndOpacity": {
        "R": 0.0,
        "G": 0.0,
        "B": 0.0,
        "A": 1.0,
        "Hex": "FF000000"
      },
      "Slot": {
        "ObjectName": "HorizontalBoxSlot WidgetArchetype:WidgetTree_0.HorizontalBox_117.HorizontalBoxSlot_0",
        "ObjectPath": "DeadByDaylight/Content/Netease/Blueprint/UI/Mobile/GameModes/CustomGame/NE_CustomGame_PyWBP_SelectMapScreen.35"
      }
    }
  },
  {
    "Type": "Image",
    "Name": "Line",
    "Outer": "WidgetTree_0",
    "Properties": {
      "Brush": {
        "ImageSize": {
          "X": 695.0,
          "Y": 3.0
        },
        "ResourceObject": {
          "ObjectName": "Texture2D GamesMode_Line_NE",
          "ObjectPath": "DeadByDaylight/Content/UI/UMGAssets/Tooltips/OutputPaper2D/Frames/GamesMode_Line_NE.0"
        }
      },
      "Slot": {
        "ObjectName": "CanvasPanelSlot WidgetArchetype:WidgetTree_0.SafeZone.CanvasPanelSlot_4",
        "ObjectPath": "DeadByDaylight/Content/Netease/Blueprint/UI/Mobile/GameModes/CustomGame/NE_CustomGame_PyWBP_SelectMapScreen.27"
      }
    }
  },
  {
    "Type": "NE_CustomGame_PyWBP_SelectMapScreen_C",
    "Name": "WidgetArchetype",
    "Template": "Default__NE_CustomGame_PyWBP_SelectMapScreen_C",
    "Properties": {
      "Background": {
        "ObjectName": "Image WidgetArchetype:WidgetTree_0.Background",
        "ObjectPath": "DeadByDaylight/Content/Netease/Blueprint/UI/Mobile/GameModes/CustomGame/NE_CustomGame_PyWBP_SelectMapScreen.41"
      },
      "BG": {
        "ObjectName": "Image WidgetArchetype:WidgetTree_0.BG",
        "ObjectPath": "DeadByDaylight/Content/Netease/Blueprint/UI/Mobile/GameModes/CustomGame/NE_CustomGame_PyWBP_SelectMapScreen.42"
      },
      "CloseButton": {
        "ObjectName": "Button WidgetArchetype:WidgetTree_0.CloseButton",
        "ObjectPath": "DeadByDaylight/Content/Netease/Blueprint/UI/Mobile/GameModes/CustomGame/NE_CustomGame_PyWBP_SelectMapScreen.5"
      },
      "ContainerPanel": {
        "ObjectName": "CanvasPanel WidgetArchetype:WidgetTree_0.ContainerPanel",
        "ObjectPath": "DeadByDaylight/Content/Netease/Blueprint/UI/Mobile/GameModes/CustomGame/NE_CustomGame_PyWBP_SelectMapScreen.11"
      },
      "Line": {
        "ObjectName": "Image WidgetArchetype:WidgetTree_0.Line",
        "ObjectPath": "DeadByDaylight/Content/Netease/Blueprint/UI/Mobile/GameModes/CustomGame/NE_CustomGame_PyWBP_SelectMapScreen.43"
      },
      "TitleLabel": {
        "ObjectName": "TextBlock WidgetArchetype:WidgetTree_0.TitleLabel",
        "ObjectPath": "DeadByDaylight/Content/Netease/Blueprint/UI/Mobile/GameModes/CustomGame/NE_CustomGame_PyWBP_SelectMapScreen.50"
      },
      "WidgetTree": {
        "ObjectName": "WidgetTree WidgetArchetype:WidgetTree_0",
        "ObjectPath": "DeadByDaylight/Content/Netease/Blueprint/UI/Mobile/GameModes/CustomGame/NE_CustomGame_PyWBP_SelectMapScreen.60"
      },
      "bCookedWidgetTree": true
    }
  },
  {
    "Type": "ScrollBox",
    "Name": "ScrollBox_0",
    "Outer": "WidgetTree",
    "Properties": {
      "Slots": [
        {
          "ObjectName": "ScrollBoxSlot NE_CustomGame_PyWBP_SelectMapScreen_C:WidgetTree.ScrollBox_0.ScrollBoxSlot_0",
          "ObjectPath": "DeadByDaylight/Content/Netease/Blueprint/UI/Mobile/GameModes/CustomGame/NE_CustomGame_PyWBP_SelectMapScreen.47"
        }
      ],
      "Slot": {
        "ObjectName": "CanvasPanelSlot NE_CustomGame_PyWBP_SelectMapScreen_C:WidgetTree.SafeZone.CanvasPanelSlot_3",
        "ObjectPath": "DeadByDaylight/Content/Netease/Blueprint/UI/Mobile/GameModes/CustomGame/NE_CustomGame_PyWBP_SelectMapScreen.19"
      },
      "Clipping": "EWidgetClipping::Inherit"
    }
  },
  {
    "Type": "ScrollBox",
    "Name": "ScrollBox_0",
    "Outer": "WidgetTree_0",
    "Properties": {
      "Slots": [
        {
          "ObjectName": "ScrollBoxSlot WidgetArchetype:WidgetTree_0.ScrollBox_0.ScrollBoxSlot_0",
          "ObjectPath": "DeadByDaylight/Content/Netease/Blueprint/UI/Mobile/GameModes/CustomGame/NE_CustomGame_PyWBP_SelectMapScreen.48"
        }
      ],
      "Slot": {
        "ObjectName": "CanvasPanelSlot WidgetArchetype:WidgetTree_0.SafeZone.CanvasPanelSlot_3",
        "ObjectPath": "DeadByDaylight/Content/Netease/Blueprint/UI/Mobile/GameModes/CustomGame/NE_CustomGame_PyWBP_SelectMapScreen.26"
      },
      "Clipping": "EWidgetClipping::Inherit"
    }
  },
  {
    "Type": "ScrollBoxSlot",
    "Name": "ScrollBoxSlot_0",
    "Outer": "ScrollBox_0",
    "Properties": {
      "Parent": {
        "ObjectName": "ScrollBox NE_CustomGame_PyWBP_SelectMapScreen_C:WidgetTree.ScrollBox_0",
        "ObjectPath": "DeadByDaylight/Content/Netease/Blueprint/UI/Mobile/GameModes/CustomGame/NE_CustomGame_PyWBP_SelectMapScreen.45"
      },
      "Content": {
        "ObjectName": "CanvasPanel NE_CustomGame_PyWBP_SelectMapScreen_C:WidgetTree.ContainerPanel",
        "ObjectPath": "DeadByDaylight/Content/Netease/Blueprint/UI/Mobile/GameModes/CustomGame/NE_CustomGame_PyWBP_SelectMapScreen.7"
      }
    }
  },
  {
    "Type": "ScrollBoxSlot",
    "Name": "ScrollBoxSlot_0",
    "Outer": "ScrollBox_0",
    "Properties": {
      "Parent": {
        "ObjectName": "ScrollBox WidgetArchetype:WidgetTree_0.ScrollBox_0",
        "ObjectPath": "DeadByDaylight/Content/Netease/Blueprint/UI/Mobile/GameModes/CustomGame/NE_CustomGame_PyWBP_SelectMapScreen.46"
      },
      "Content": {
        "ObjectName": "CanvasPanel WidgetArchetype:WidgetTree_0.ContainerPanel",
        "ObjectPath": "DeadByDaylight/Content/Netease/Blueprint/UI/Mobile/GameModes/CustomGame/NE_CustomGame_PyWBP_SelectMapScreen.11"
      }
    }
  },
  {
    "Type": "TextBlock",
    "Name": "TitleLabel",
    "Outer": "WidgetTree",
    "Properties": {
      "Text": {
        "CultureInvariantString": "Select Map"
      },
      "Font": {
        "Size": 36
      },
      "AutoWrapText": true,
      "Slot": {
        "ObjectName": "VerticalBoxSlot NE_CustomGame_PyWBP_SelectMapScreen_C:WidgetTree.VerticalBox_0.VerticalBoxSlot_0",
        "ObjectPath": "DeadByDaylight/Content/Netease/Blueprint/UI/Mobile/GameModes/CustomGame/NE_CustomGame_PyWBP_SelectMapScreen.55"
      },
      "bIsVariable": true,
      "Visibility": "ESlateVisibility::SelfHitTestInvisible"
    }
  },
  {
    "Type": "TextBlock",
    "Name": "TitleLabel",
    "Outer": "WidgetTree_0",
    "Properties": {
      "Text": {
        "CultureInvariantString": "Select Map"
      },
      "Font": {
        "Size": 36
      },
      "AutoWrapText": true,
      "Slot": {
        "ObjectName": "VerticalBoxSlot WidgetArchetype:WidgetTree_0.VerticalBox_0.VerticalBoxSlot_0",
        "ObjectPath": "DeadByDaylight/Content/Netease/Blueprint/UI/Mobile/GameModes/CustomGame/NE_CustomGame_PyWBP_SelectMapScreen.57"
      },
      "bIsVariable": true,
      "Visibility": "ESlateVisibility::SelfHitTestInvisible"
    }
  },
  {
    "Type": "VerticalBox",
    "Name": "VerticalBox_0",
    "Outer": "WidgetTree",
    "Properties": {
      "Slots": [
        {
          "ObjectName": "VerticalBoxSlot NE_CustomGame_PyWBP_SelectMapScreen_C:WidgetTree.VerticalBox_0.VerticalBoxSlot_0",
          "ObjectPath": "DeadByDaylight/Content/Netease/Blueprint/UI/Mobile/GameModes/CustomGame/NE_CustomGame_PyWBP_SelectMapScreen.55"
        }
      ],
      "Slot": {
        "ObjectName": "CanvasPanelSlot NE_CustomGame_PyWBP_SelectMapScreen_C:WidgetTree.Header.CanvasPanelSlot_2",
        "ObjectPath": "DeadByDaylight/Content/Netease/Blueprint/UI/Mobile/GameModes/CustomGame/NE_CustomGame_PyWBP_SelectMapScreen.17"
      }
    }
  },
  {
    "Type": "VerticalBox",
    "Name": "VerticalBox_595",
    "Outer": "WidgetTree",
    "Properties": {
      "Slots": [
        {
          "ObjectName": "VerticalBoxSlot NE_CustomGame_PyWBP_SelectMapScreen_C:WidgetTree.VerticalBox_595.VerticalBoxSlot_1",
          "ObjectPath": "DeadByDaylight/Content/Netease/Blueprint/UI/Mobile/GameModes/CustomGame/NE_CustomGame_PyWBP_SelectMapScreen.56"
        }
      ],
      "Slot": {
        "ObjectName": "HorizontalBoxSlot NE_CustomGame_PyWBP_SelectMapScreen_C:WidgetTree.HorizontalBox_189.HorizontalBoxSlot_0",
        "ObjectPath": "DeadByDaylight/Content/Netease/Blueprint/UI/Mobile/GameModes/CustomGame/NE_CustomGame_PyWBP_SelectMapScreen.34"
      }
    }
  },
  {
    "Type": "VerticalBox",
    "Name": "VerticalBox_0",
    "Outer": "WidgetTree_0",
    "Properties": {
      "Slots": [
        {
          "ObjectName": "VerticalBoxSlot WidgetArchetype:WidgetTree_0.VerticalBox_0.VerticalBoxSlot_0",
          "ObjectPath": "DeadByDaylight/Content/Netease/Blueprint/UI/Mobile/GameModes/CustomGame/NE_CustomGame_PyWBP_SelectMapScreen.57"
        }
      ],
      "Slot": {
        "ObjectName": "CanvasPanelSlot WidgetArchetype:WidgetTree_0.Header.CanvasPanelSlot_2",
        "ObjectPath": "DeadByDaylight/Content/Netease/Blueprint/UI/Mobile/GameModes/CustomGame/NE_CustomGame_PyWBP_SelectMapScreen.24"
      }
    }
  },
  {
    "Type": "VerticalBox",
    "Name": "VerticalBox_595",
    "Outer": "WidgetTree_0",
    "Properties": {
      "Slots": [
        {
          "ObjectName": "VerticalBoxSlot WidgetArchetype:WidgetTree_0.VerticalBox_595.VerticalBoxSlot_1",
          "ObjectPath": "DeadByDaylight/Content/Netease/Blueprint/UI/Mobile/GameModes/CustomGame/NE_CustomGame_PyWBP_SelectMapScreen.58"
        }
      ],
      "Slot": {
        "ObjectName": "HorizontalBoxSlot WidgetArchetype:WidgetTree_0.HorizontalBox_189.HorizontalBoxSlot_0",
        "ObjectPath": "DeadByDaylight/Content/Netease/Blueprint/UI/Mobile/GameModes/CustomGame/NE_CustomGame_PyWBP_SelectMapScreen.37"
      }
    }
  },
  {
    "Type": "VerticalBoxSlot",
    "Name": "VerticalBoxSlot_0",
    "Outer": "VerticalBox_0",
    "Properties": {
      "Padding": {
        "Left": 86.0
      },
      "VerticalAlignment": "VAlign_Center",
      "Parent": {
        "ObjectName": "VerticalBox NE_CustomGame_PyWBP_SelectMapScreen_C:WidgetTree.VerticalBox_0",
        "ObjectPath": "DeadByDaylight/Content/Netease/Blueprint/UI/Mobile/GameModes/CustomGame/NE_CustomGame_PyWBP_SelectMapScreen.51"
      },
      "Content": {
        "ObjectName": "TextBlock NE_CustomGame_PyWBP_SelectMapScreen_C:WidgetTree.TitleLabel",
        "ObjectPath": "DeadByDaylight/Content/Netease/Blueprint/UI/Mobile/GameModes/CustomGame/NE_CustomGame_PyWBP_SelectMapScreen.49"
      }
    }
  },
  {
    "Type": "VerticalBoxSlot",
    "Name": "VerticalBoxSlot_1",
    "Outer": "VerticalBox_595",
    "Properties": {
      "Size": {
        "SizeRule": "ESlateSizeRule::Fill"
      },
      "Parent": {
        "ObjectName": "VerticalBox NE_CustomGame_PyWBP_SelectMapScreen_C:WidgetTree.VerticalBox_595",
        "ObjectPath": "DeadByDaylight/Content/Netease/Blueprint/UI/Mobile/GameModes/CustomGame/NE_CustomGame_PyWBP_SelectMapScreen.52"
      },
      "Content": {
        "ObjectName": "CanvasPanel NE_CustomGame_PyWBP_SelectMapScreen_C:WidgetTree.SafeZone",
        "ObjectPath": "DeadByDaylight/Content/Netease/Blueprint/UI/Mobile/GameModes/CustomGame/NE_CustomGame_PyWBP_SelectMapScreen.9"
      }
    }
  },
  {
    "Type": "VerticalBoxSlot",
    "Name": "VerticalBoxSlot_0",
    "Outer": "VerticalBox_0",
    "Properties": {
      "Padding": {
        "Left": 86.0
      },
      "VerticalAlignment": "VAlign_Center",
      "Parent": {
        "ObjectName": "VerticalBox WidgetArchetype:WidgetTree_0.VerticalBox_0",
        "ObjectPath": "DeadByDaylight/Content/Netease/Blueprint/UI/Mobile/GameModes/CustomGame/NE_CustomGame_PyWBP_SelectMapScreen.53"
      },
      "Content": {
        "ObjectName": "TextBlock WidgetArchetype:WidgetTree_0.TitleLabel",
        "ObjectPath": "DeadByDaylight/Content/Netease/Blueprint/UI/Mobile/GameModes/CustomGame/NE_CustomGame_PyWBP_SelectMapScreen.50"
      }
    }
  },
  {
    "Type": "VerticalBoxSlot",
    "Name": "VerticalBoxSlot_1",
    "Outer": "VerticalBox_595",
    "Properties": {
      "Size": {
        "SizeRule": "ESlateSizeRule::Fill"
      },
      "Parent": {
        "ObjectName": "VerticalBox WidgetArchetype:WidgetTree_0.VerticalBox_595",
        "ObjectPath": "DeadByDaylight/Content/Netease/Blueprint/UI/Mobile/GameModes/CustomGame/NE_CustomGame_PyWBP_SelectMapScreen.54"
      },
      "Content": {
        "ObjectName": "CanvasPanel WidgetArchetype:WidgetTree_0.SafeZone",
        "ObjectPath": "DeadByDaylight/Content/Netease/Blueprint/UI/Mobile/GameModes/CustomGame/NE_CustomGame_PyWBP_SelectMapScreen.13"
      }
    }
  },
  {
    "Type": "WidgetTree",
    "Name": "WidgetTree",
    "Outer": "NE_CustomGame_PyWBP_SelectMapScreen_C",
    "Properties": {
      "RootWidget": {
        "ObjectName": "CanvasPanel NE_CustomGame_PyWBP_SelectMapScreen_C:WidgetTree.CanvasPanel_0",
        "ObjectPath": "DeadByDaylight/Content/Netease/Blueprint/UI/Mobile/GameModes/CustomGame/NE_CustomGame_PyWBP_SelectMapScreen.6"
      }
    }
  },
  {
    "Type": "WidgetTree",
    "Name": "WidgetTree_0",
    "Outer": "WidgetArchetype",
    "Properties": {
      "RootWidget": {
        "ObjectName": "CanvasPanel WidgetArchetype:WidgetTree_0.CanvasPanel_0",
        "ObjectPath": "DeadByDaylight/Content/Netease/Blueprint/UI/Mobile/GameModes/CustomGame/NE_CustomGame_PyWBP_SelectMapScreen.10"
      }
    }
  }
]